Metadata-Version: 2.1
Name: tgs13
Version: 0.1.0
Summary: Third tea package dependent on tgs11 and tgs12
Home-page: https://github.com/ganisacik/tgs13
Author: ganisacik
Author-email: senin-email@example.com
License: UNKNOWN
Project-URL: Source, https://github.com/ganisacik/tgs13
Platform: UNKNOWN
